topsis/__init__.py
topsis/topsis.py
topsis_pypck/__init__.py
topsis_pypck/topsis.py
topsis_pypck-0.2.2.dist-info/LICENSE
topsis_pypck-0.2.2.dist-info/METADATA
topsis_pypck-0.2.2.dist-info/WHEEL
topsis_pypck-0.2.2.dist-info/top_level.txt
topsis_pypck-0.2.2.dist-info/RECORD
